{
  "law": "OR",
  "article": "259a",
  "header": "Art. 259a, Rechte des Mieters, Im allgemeinen",
  "text": "1 Entstehen an der Sache Mängel, die der Mieter weder zu verantworten noch auf eigene\nKosten zu beseitigen hat, oder wird der Mieter im vertragsgemässen Gebrauch der Sache\ngestört, so kann er verlangen, dass der Vermieter:\na. den Mangel beseitigt;\nb. den Mietzins verhältnismässig herabsetzt;\nc. Schadenersatz leistet;\nd. den Rechtsstreit mit einem Dritten übernimmt.\n2 Der Mieter einer unbeweglichen Sache kann zudem den Mietzins hinterlegen.",
  "source": "OR.pdf"
}