{
  "law": "OR",
  "article": "253b",
  "header": "Art. 253b, Bestimmungen über den Schutz vor missbräuchlichen Mietzinsen",
  "text": "1 Die Bestimmungen über den Schutz vor missbräuchlichen Mietzinsen (Art. 269 ff.) gelten\nsinngemäss für nichtlandwirtschaftliche Pacht- und andere Verträge, die im wesentlichen die\nÜberlassung von Wohn- oder Geschäftsräumen gegen Entgelt regeln.\n2 Sie gelten nicht für die Miete von luxuriösen Wohnungen und Einfamilienhäusern mit sechs\noder mehr Wohnräumen (ohne Anrechnung der Küche).\n3 Die Bestimmungen über die Anfechtung missbräuchlicher Mietzinse gelten nicht für Wohnräume,\nderen Bereitstellung von der öffentlichen Hand gefördert wurde und deren Mietzinse\ndurch eine Behörde kontrolliert werden.",
  "source": "OR.pdf"
}